brainfuk/pybf.py
brainfuk-0.0.2.dist-info/LICENSE.txt
brainfuk-0.0.2.dist-info/METADATA
brainfuk-0.0.2.dist-info/WHEEL
brainfuk-0.0.2.dist-info/entry_points.txt
brainfuk-0.0.2.dist-info/top_level.txt
brainfuk-0.0.2.dist-info/RECORD
