Metadata-Version: 2.1
Name: brainfuk
Version: 0.0.2
Author-email: Nater0214 <gamer@nater0214.com>
License: GNU GENERAL PUBLIC LICENSE
Requires-Python: >=3.10
License-File: LICENSE.txt
Requires-Dist: naters-utils
Provides-Extra: dev
Requires-Dist: pytest ; extra == 'dev'
